theohe_epias/__init__.py
theohe_epias/epys/__init__.py
theohe_epias/epys/service.py
theohe_epias/epys/collateral/__init__.py
theohe_epias/epys/eligible_customer/__init__.py
theohe_epias/epys/eligible_customer/eligible_customer_meter.py
theohe_epias/epys/invoice/__init__.py
theohe_epias/epys/invoice/data.py
theohe_epias/epys/reconciliation/__init__.py
theohe_epias/epys/reconciliation/advance.py
theohe_epias/epys/reconciliation/bpm.py
theohe_epias/epys/reconciliation/imbalance.py
theohe_epias/epys/reconciliation/renewables.py
theohe_epias/epys/reconciliation/reports.py
theohe_epias/epys/reconciliation/settlement.py
theohe_epias/epys/reconciliation/settlementdata.py
theohe_epias/epys/registration/__init__.py
theohe_epias/epys/registration/organization.py
theohe_epias/epys/registration/registrationmeter.py
theohe_epias/epys/unlicensed/__init__.py
theohe_epias/epys/unlicensed/luytob_control.py
theohe_epias/epys/utils/__init__.py
theohe_epias/epys/utils/get_time.py
theohe_epias/epys/utils/tgt.py
theohe_epias/epys/utils/time_format.py
theohe_epias/transparency/__init__.py
theohe_epias/transparency/service.py
theohe_epias/transparency/data/__init__.py
theohe_epias/transparency/data/ancillary_services.py
theohe_epias/transparency/data/bilateral_contracts.py
theohe_epias/transparency/data/bpm.py
theohe_epias/transparency/data/consumption.py
theohe_epias/transparency/data/dam.py
theohe_epias/transparency/data/dams.py
theohe_epias/transparency/data/general_data.py
theohe_epias/transparency/data/idm.py
theohe_epias/transparency/data/imbalance.py
theohe_epias/transparency/data/mms.py
theohe_epias/transparency/data/pfm.py
theohe_epias/transparency/data/production.py
theohe_epias/transparency/data/renewables.py
theohe_epias/transparency/data/reports.py
theohe_epias/transparency/data/transmission.py
theohe_epias/transparency/data/yekg.py
theohe_epias/transparency/utils/__init__.py
theohe_epias/transparency/utils/get_time.py
theohe_epias/transparency/utils/time_format.py
theohe_epias-0.0.13.dist-info/LICENSE
theohe_epias-0.0.13.dist-info/METADATA
theohe_epias-0.0.13.dist-info/WHEEL
theohe_epias-0.0.13.dist-info/top_level.txt
theohe_epias-0.0.13.dist-info/RECORD
