Metadata-Version: 2.1
Name: theohe-epias
Version: 0.0.13
Summary: Energy Exchange Istanbul (EXIST) or Enerji Piyasaları İşletme A.Ş. (EPİAŞ) by its Turkish name is an energy exchange company.
Author-email: Onur Hakkı Eyüboğlu <eyubogluo@itu.edu.tr>
Project-URL: Homepage, https://github.com/onurhakki/exist
Classifier: Programming Language :: Python :: 3
Classifier: License :: OSI Approved :: MIT License
Classifier: Operating System :: OS Independent
Requires-Python: >=3.8
License-File: LICENSE
Requires-Dist: requests
Requires-Dist: pandas
Requires-Dist: pwinput
